starlette_graphene/__init__.py
starlette_graphene/version.py
tests/__init__.py
tests/conftest.py
tests/test_main.py
starlette_graphene-0.4.0.dist-info/LICENSE
starlette_graphene-0.4.0.dist-info/METADATA
starlette_graphene-0.4.0.dist-info/WHEEL
starlette_graphene-0.4.0.dist-info/top_level.txt
starlette_graphene-0.4.0.dist-info/RECORD
